{
	"$schema": "http://schema.management.azure.com/schemas/2015-01-01/deploymentTemplate.json#",
	"contentVersion": "1.0.0.0",
	"parameters": {
		"factoryName": {
			"type": "string",
			"metadata": "Data Factory Name"
		},
		"Sql_OnMyLaptop": {
			"type": "string"
		},
		"AzureStorageLinkedService": {
			"type": "string"
		}
	},
	"variables": {
		"factoryId": "[concat('Microsoft.DataFactory/factories/', parameters('factoryName'))]"
	},
	"resources": [
		{
			"name": "[concat(parameters('factoryName'), '/SQLServerToBlobPipeline')]",
			"type": "Microsoft.DataFactory/factories/pipelines",
			"apiVersion": "2018-06-01",
			"properties": {
				"activities": [
					{
						"name": "CopySqlServerToAzureBlobActivity",
						"type": "Copy",
						"policy": {
							"timeout": "7.00:00:00",
							"retry": 0,
							"retryIntervalInSeconds": 30,
							"secureOutput": false,
							"secureInput": false
						},
						"typeProperties": {
							"source": {
								"type": "SqlServerSource"
							},
							"sink": {
								"type": "BlobSink"
							},
							"enableStaging": false
						},
						"inputs": [
							{
								"referenceName": "SqlServerTable1",
								"type": "DatasetReference"
							}
						],
						"outputs": [
							{
								"referenceName": "AzureBlobDataset",
								"type": "DatasetReference"
							}
						]
					}
				]
			},
			"dependsOn": [
				"[concat(variables('factoryId'), '/datasets/SqlServerTable1')]",
				"[concat(variables('factoryId'), '/datasets/AzureBlobDataset')]"
			]
		},
		{
			"name": "[concat(parameters('factoryName'), '/SqlServerTable1')]",
			"type": "Microsoft.DataFactory/factories/datasets",
			"apiVersion": "2018-06-01",
			"properties": {
				"linkedServiceName": {
					"referenceName": "[parameters('Sql_OnMyLaptop')]",
					"type": "LinkedServiceReference"
				},
				"type": "SqlServerTable",
				"schema": [
					{
						"name": "ID",
						"type": "int",
						"precision": 10
					},
					{
						"name": "FirstName",
						"type": "varchar"
					},
					{
						"name": "LastName",
						"type": "varchar"
					}
				],
				"typeProperties": {
					"tableName": "[concat('[', 'dbo].[emp]')]"
				}
			}
		},
		{
			"name": "[concat(parameters('factoryName'), '/AzureBlobDataset')]",
			"type": "Microsoft.DataFactory/factories/datasets",
			"apiVersion": "2018-06-01",
			"properties": {
				"linkedServiceName": {
					"referenceName": "[parameters('AzureStorageLinkedService')]",
					"type": "LinkedServiceReference"
				},
				"type": "AzureBlob",
				"typeProperties": {
					"fileName": {
						"value": "@CONCAT(pipeline().RunId, '.txt')",
						"type": "Expression"
					},
					"folderPath": "adftutorial/fromonprem"
				}
			}
		}
	]
}